{
  "elements": [
    {
      "id": "f0c347b5-a3cc-4a92-8c44-97792b74f30b",
      "categoryId": "flowchart",
      "description": "a simple flowchart with top to down direction",
      "content": "flowchart TD\nStart --> Stop",
      "sortingOrder": 1,
      "isPinned": false
    },
    {
      "id": "c53dc28a-9f22-44b1-ae77-b1e1bfac570b",
      "categoryId": "flowchart",
      "description": "a simple flowchart with left to right direction",
      "content": "flowchart LR\nStart --> Stop",
      "sortingOrder": 2,
      "isPinned": false
    },
    {
      "id": "f990dbe3-9f21-4946-ab47-e730c52bf364",
      "categoryId": "flowchart",
      "description": "A node with round edges",
      "content": "id1(Some text)",
      "sortingOrder": 3,
      "isPinned": false
    },
    {
      "id": "683819bf-11a4-498f-b030-2de6425f17d6",
      "categoryId": "flowchart",
      "description": "A stadium-shaped node",
      "content": "id1([Some text])",
      "sortingOrder": 4,
      "isPinned": false
    },
    {
      "id": "8fd08206-a03a-4aac-a4d2-63e986b18e59",
      "categoryId": "flowchart",
      "description": "A node in a cylindrical shape",
      "content": "id1[(Database)]",
      "sortingOrder": 5,
      "isPinned": false
    },
    {
      "id": "ae1d9eaf-f651-47cf-9df9-9ae35ec67364",
      "categoryId": "flowchart",
      "description": "Circle",
      "content": "id1((Some text))",
      "sortingOrder": 6,
      "isPinned": false
    },
    {
      "id": "4e622ac5-5364-40db-9c5d-a4fd748975ba",
      "categoryId": "flowchart",
      "description": "Rhombus",
      "content": "id1{Some text}",
      "sortingOrder": 7,
      "isPinned": false
    },
    {
      "id": "50dac19f-cdfd-41fc-aa04-94079f9e87bb",
      "categoryId": "flowchart",
      "description": "Hexagon",
      "content": "id1{{Some text}}",
      "sortingOrder": 8,
      "isPinned": false
    },
    {
      "id": "15f50463-f313-49f6-a664-59b295b6732c",
      "categoryId": "flowchart",
      "description": "Parallelogram skewed right",
      "content": "id1[/Some text/]",
      "sortingOrder": 9,
      "isPinned": false
    },
    {
      "id": "4d408fab-0d25-4d74-aefb-81afd4621fcd",
      "categoryId": "flowchart",
      "description": "Parallelogram skewed left",
      "content": "id1[\\Some text\\]",
      "sortingOrder": 10,
      "isPinned": false
    },
    {
      "id": "47623909-4c60-4d3f-98b9-176adc25076d",
      "categoryId": "flowchart",
      "description": "Trapezoid",
      "content": "A[/Some text\\]",
      "sortingOrder": 11,
      "isPinned": false
    },
    {
      "id": "a93f9ece-69fb-4023-bd13-5d5f9c31c322",
      "categoryId": "flowchart",
      "description": "Trapezoid upside down",
      "content": "A[\\Some text/]",
      "sortingOrder": 12,
      "isPinned": false
    },
    {
      "id": "28ad4d23-5aa1-4fd6-b5b0-6fd6f2adf42a",
      "categoryId": "flowchart",
      "description": "Double circle node",
      "content": "id1(((Some text)))",
      "sortingOrder": 13,
      "isPinned": false
    },
    {
      "id": "7ada80f0-7250-43a5-8213-4d451e06d0d7",
      "categoryId": "flowchart",
      "description": "A link with arrow head",
      "content": "A-->B",
      "sortingOrder": 14,
      "isPinned": false
    },
    {
      "id": "197b5fd8-cd9e-4f58-9b0c-7b85aeb050ce",
      "categoryId": "flowchart",
      "description": "An open link",
      "content": "A --- B",
      "sortingOrder": 15,
      "isPinned": false
    },
    {
      "id": "d9e6444e-dde0-49ce-964e-2c676a4ba10b",
      "categoryId": "flowchart",
      "description": "Text on links",
      "content": "A-- This is the text! ---B",
      "sortingOrder": 16,
      "isPinned": false
    },
    {
      "id": "a5b7f276-fee5-48e3-aa18-1ce9f63d7813",
      "categoryId": "flowchart",
      "description": "A link with arrow head and text",
      "content": "A-->|text|B",
      "sortingOrder": 17,
      "isPinned": false
    },
    {
      "id": "a12be60a-4d67-4657-a62d-29f22119f239",
      "categoryId": "flowchart",
      "description": "Dotted link",
      "content": "A-.->B",
      "sortingOrder": 18,
      "isPinned": false
    },
    {
      "id": "074079a6-7c92-4bbd-8d6e-dde725a0e2f2",
      "categoryId": "flowchart",
      "description": "Thick link",
      "content": "A ==> B",
      "sortingOrder": 19,
      "isPinned": false
    },
    {
      "id": "50c892da-40d6-492b-93e5-4e6152b9576c",
      "categoryId": "flowchart",
      "description": "Invisible link",
      "content": "A ~~~ B",
      "sortingOrder": 20,
      "isPinned": false
    },
    {
      "id": "cee4e4fa-e788-4f3c-8a99-fcf3dff25b67",
      "categoryId": "flowchart",
      "description": "Link with circle edge",
      "content": "A --o B",
      "sortingOrder": 21,
      "isPinned": false
    },
    {
      "id": "c4e63526-f516-4af3-b13e-646935c9a160",
      "categoryId": "flowchart",
      "description": "Link with cross edge",
      "content": "A --x B",
      "sortingOrder": 22,
      "isPinned": false
    },
    {
      "id": "2918054a-b988-4316-ba43-34f648390768",
      "categoryId": "flowchart",
      "description": "Subgraph",
      "content": "subgraph one\na1-->a2\nend",
      "sortingOrder": 14,
      "isPinned": false
    },
    {
      "id": "17d2dc46-caa6-4766-9668-a30aedd52c08",
      "categoryId": "sequenceDiagram",
      "description": "a simple sequence diagram",
      "content": "sequenceDiagram\nAlice->>John: Hello John, how are you?\nJohn-->>Alice: Great!\nAlice-)John: See you later!",
      "sortingOrder": 0,
      "isPinned": false
    },
    {
      "id": "e6299aa1-f4bd-4510-be7e-6229a5dbbd01",
      "categoryId": "sequenceDiagram",
      "description": "a simple sequence diagram with actors",
      "content": "sequenceDiagram\nactor Alice\nactor John\nAlice->>John: Hello John, how are you?\nJohn-->>Alice: Great!\nAlice-)John: See you later!",
      "sortingOrder": 1,
      "isPinned": false
    },
    {
      "id": "e2230680-f55c-44e1-b10c-94c6eb544c76",
      "categoryId": "classDiagram",
      "description": "sample class",
      "content": "class Duck{\n            +String beakColor\n            +swim()\n            +quack()\n        }",
      "sortingOrder": 0,
      "isPinned": false
    },
    {
      "id": "e9ed51de-8ff3-4380-a5bc-714962648087",
      "categoryId": "classDiagram",
      "description": "sample class",
      "content": "class BankAccount\n        BankAccount : +String owner\n        BankAccount : +Bigdecimal balance\n        BankAccount : +deposit(amount)\n        BankAccount : +withdrawal(amount)",
      "sortingOrder": 1,
      "isPinned": false
    },
    {
      "id": "411c98cd-aa0e-47cf-84b0-2cae62c08f43",
      "categoryId": "classDiagram",
      "description": "generic class",
      "content": "class Square~Shape~{\n            int id\n            List~int~ position\n            setPoints(List~int~ points)\n            getPoints() List~int~\n        }\n        \n        Square : -List~string~ messages\n        Square : +setMessages(List~string~ messages)\n        Square : +getMessages() List~string~",
      "sortingOrder": 2,
      "isPinned": false
    },
    {
      "id": "9185974c-89ec-42f0-befd-3776a26bfd8c",
      "categoryId": "classDiagram",
      "description": "inheritance",
      "content": "classA <|-- classB",
      "sortingOrder": 3,
      "isPinned": false
    },
    {
      "id": "176b0fe7-9e9f-44f7-842d-ea608e165cbc",
      "categoryId": "classDiagram",
      "description": "composition",
      "content": "classC *-- classD",
      "sortingOrder": 4,
      "isPinned": false
    },
    {
      "id": "d09ffea3-c3ce-4634-8a2d-0058f0b9b0b2",
      "categoryId": "classDiagram",
      "description": "aggregation",
      "content": "classE o-- classF",
      "sortingOrder": 5,
      "isPinned": false
    },
    {
      "id": "5c6c6d7c-76d1-4c9b-810e-cebd3733f0b2",
      "categoryId": "classDiagram",
      "description": "association",
      "content": "classG <-- classH",
      "sortingOrder": 6,
      "isPinned": false
    },
    {
      "id": "aee597ec-56ff-4884-8082-2d95636a9d2a",
      "categoryId": "classDiagram",
      "description": "solid link",
      "content": "classI -- classJ",
      "sortingOrder": 7,
      "isPinned": false
    },
    {
      "id": "945ecc9b-f064-42fa-b3ef-3330699ddb70",
      "categoryId": "classDiagram",
      "description": "dependency",
      "content": "classK <.. classL",
      "sortingOrder": 8,
      "isPinned": false
    },
    {
      "id": "378ee566-1ca2-4b65-8c56-b2b7a8d29825",
      "categoryId": "classDiagram",
      "description": "realization",
      "content": "classM <|.. classN",
      "sortingOrder": 9,
      "isPinned": false
    },
    {
      "id": "8355de30-1b82-4614-b715-b0d784c25a2a",
      "categoryId": "classDiagram",
      "description": "dashed link",
      "content": "classO .. classP",
      "sortingOrder": 10,
      "isPinned": false
    },
    {
      "id": "5717ae76-ce58-4167-ad21-8e47691e5fbb",
      "categoryId": "classDiagram",
      "description": "two-way relation",
      "content": "Animal <|--|> Zebra",
      "sortingOrder": 11,
      "isPinned": false
    },
    {
      "id": "18220087-341f-4367-82ce-7374a87d04b2",
      "categoryId": "classDiagram",
      "description": "sample class diagram",
      "content": "classDiagram\n        Animal <|-- Duck\n        Animal <|-- Fish\n        Animal <|-- Zebra\n        Animal : +int age\n        Animal : +String gender\n        Animal: +isMammal()\n        Animal: +mate()\n        class Duck{\n            +String beakColor\n            +swim()\n            +quack()\n        }\n        class Fish{\n            -int sizeInFeet\n            -canEat()\n        }\n        class Zebra{\n            +bool is_wild\n            +run()\n        }",
      "sortingOrder": 12,
      "isPinned": false
    },
    {
      "id": "0305fae7-f21f-4b03-bd5a-c7c88a6fc743",
      "categoryId": "stateDiagram",
      "description": "a sample state diagram",
      "content": "stateDiagram-v2\n        [*] --> Still\n        Still --> [*]\n    \n        Still --> Moving\n        Moving --> Still\n        Moving --> Crash\n        Crash --> [*]",
      "sortingOrder": 0,
      "isPinned": false
    },
    {
      "id": "fbe202bf-5a35-4214-8857-3a84ca86f132",
      "categoryId": "stateDiagram",
      "description": "a sample state diagram with left-to-right direction",
      "content": "stateDiagram-v2\n        direction LR\n        [*] --> Still\n        Still --> [*]\n    \n        Still --> Moving\n        Moving --> Still\n        Moving --> Crash\n        Crash --> [*]",
      "sortingOrder": 1,
      "isPinned": false
    },
    {
      "id": "ac12f6ea-f85b-401f-aa81-74ac81415667",
      "categoryId": "stateDiagram",
      "description": "node with description",
      "content": "s2 : This is a state description",
      "sortingOrder": 2,
      "isPinned": false
    },
    {
      "id": "b30a6570-7a55-4460-9692-59572f4f18a9",
      "categoryId": "stateDiagram",
      "description": "a transition",
      "content": "s1 --> s2",
      "sortingOrder": 3,
      "isPinned": false
    },
    {
      "id": "03e64f57-9724-40bd-b2d9-32add843ab3d",
      "categoryId": "stateDiagram",
      "description": "a transition with label",
      "content": "s1 --> s2: A transition",
      "sortingOrder": 4,
      "isPinned": false
    },
    {
      "id": "26da9075-cc63-4c8d-bd6b-e04e66fd26d9",
      "categoryId": "stateDiagram",
      "description": "composite state",
      "content": "\n        [*] --> First\n        state First {\n            [*] --> second\n            second --> [*]\n        }",
      "sortingOrder": 5,
      "isPinned": false
    },
    {
      "id": "37964c1e-29c3-43ee-991b-678ca8295b47",
      "categoryId": "stateDiagram",
      "description": "diagram with choice",
      "content": "stateDiagram-v2\n        state if_state <<choice>>\n        [*] --> IsPositive\n        IsPositive --> if_state\n        if_state --> False: if n < 0\n        if_state --> True : if n >= 0",
      "sortingOrder": 6,
      "isPinned": false
    },
    {
      "id": "6266c280-f399-4f19-b97d-b317217544f1",
      "categoryId": "stateDiagram",
      "description": "diagram with fork",
      "content": "stateDiagram-v2\n        state fork_state <<fork>>\n          [*] --> fork_state\n          fork_state --> State2\n          fork_state --> State3\n    \n          state join_state <<join>>\n          State2 --> join_state\n          State3 --> join_state\n          join_state --> State4\n          State4 --> [*]",
      "sortingOrder": 7,
      "isPinned": false
    },
    {
      "id": "f710c079-8296-4600-832a-118219a957da",
      "categoryId": "stateDiagram",
      "description": "a diagram with concurrency",
      "content": "stateDiagram-v2\n        [*] --> Active\n    \n        state Active {\n            [*] --> NumLockOff\n            NumLockOff --> NumLockOn : EvNumLockPressed\n            NumLockOn --> NumLockOff : EvNumLockPressed\n            --\n            [*] --> CapsLockOff\n            CapsLockOff --> CapsLockOn : EvCapsLockPressed\n            CapsLockOn --> CapsLockOff : EvCapsLockPressed\n            --\n            [*] --> ScrollLockOff\n            ScrollLockOff --> ScrollLockOn : EvScrollLockPressed\n            ScrollLockOn --> ScrollLockOff : EvScrollLockPressed\n        }",
      "sortingOrder": 8,
      "isPinned": false
    },
    {
      "id": "23998ffc-63fd-4729-960e-54633c885ba7",
      "categoryId": "entityRelationshipDiagram",
      "description": "a sample entity relationship diagram",
      "content": "erDiagram\n        CUSTOMER ||--o{ ORDER : places\n        ORDER ||--|{ LINE-ITEM : contains\n        CUSTOMER }|..|{ DELIVERY-ADDRESS : uses",
      "sortingOrder": 0,
      "isPinned": false
    },
    {
      "id": "4fc1686f-7ea4-411b-9ecb-88dbfb898b4e",
      "categoryId": "entityRelationshipDiagram",
      "description": "an entity",
      "content": "    CUSTOMER {\n            string name\n            string custNumber\n            string sector\n        }",
      "sortingOrder": 1,
      "isPinned": false
    },
    {
      "id": "c2cd6adf-4225-4170-b125-977a2ba14b0b",
      "categoryId": "entityRelationshipDiagram",
      "description": "one-to-many relationship",
      "content": "A ||--|{ B : label",
      "sortingOrder": 2,
      "isPinned": false
    },
    {
      "id": "bc376e45-3a2c-4f0c-853b-33f9a9751745",
      "categoryId": "entityRelationshipDiagram",
      "description": "many-to-many relationship",
      "content": "A }|--|{ B : label",
      "sortingOrder": 3,
      "isPinned": false
    },
    {
      "id": "a632f235-07c0-4978-ab99-76be01528c90",
      "categoryId": "entityRelationshipDiagram",
      "description": "one-to-one relationship",
      "content": "A ||--|| B : label",
      "sortingOrder": 4,
      "isPinned": false
    },
    {
      "id": "487aeb72-58e9-4b94-81e3-588e855ee118",
      "categoryId": "entityRelationshipDiagram",
      "description": "many-to-one relationship",
      "content": "A }|--|| B : label",
      "sortingOrder": 5,
      "isPinned": false
    },
    {
      "id": "89629405-51a5-4f47-8a74-c9d9e0d546d4",
      "categoryId": "entityRelationshipDiagram",
      "description": "zero/one-to-one relationship",
      "content": "A |o--|| B : label",
      "sortingOrder": 6,
      "isPinned": false
    },
    {
      "id": "064c567a-542d-4a55-8075-8255d118dc3a",
      "categoryId": "entityRelationshipDiagram",
      "description": "one-to-one/zero relationship",
      "content": "A ||--o| B : label",
      "sortingOrder": 7,
      "isPinned": false
    },
    {
      "id": "9f8ac427-428c-4fc5-9465-f2e9d49b63ff",
      "categoryId": "entityRelationshipDiagram",
      "description": "zero-or-more-to-one relationship",
      "content": "A }o--|| B : label",
      "sortingOrder": 8,
      "isPinned": false
    },
    {
      "id": "81d977cb-dd70-46cc-9727-cb9e16f0eb30",
      "categoryId": "entityRelationshipDiagram",
      "description": "one-to-zero-or-more relationship",
      "content": "A ||--o{ B : label",
      "sortingOrder": 9,
      "isPinned": false
    },
    {
      "id": "61750fb2-cc43-49dd-8a7f-be107643cb08",
      "categoryId": "entityRelationshipDiagram",
      "description": "zero-or-more-to-many relationship",
      "content": "A }o--|{ B : label",
      "sortingOrder": 10,
      "isPinned": false
    },
    {
      "id": "cfb79504-c1b5-4c53-9d47-e2ed18b6ab54",
      "categoryId": "entityRelationshipDiagram",
      "description": "many-to-zero-or-more relationship",
      "content": "A }|--o{ B : label",
      "sortingOrder": 11,
      "isPinned": false
    },
    {
      "id": "dd88ab2f-7860-4aff-acfb-ec75c0137274",
      "categoryId": "userJourneyDiagram",
      "description": "a sample user journey diagram",
      "content": "journey\n        title My working day\n        section Go to work\n          Make tea: 5: Me\n          Go upstairs: 3: Me\n          Do work: 1: Me, Cat\n        section Go home\n          Go downstairs: 5: Me\n          Sit down: 5: Me",
      "sortingOrder": 0,
      "isPinned": false
    },
    {
      "id": "bb860f7e-8332-44bc-85b2-1e41698880d9",
      "categoryId": "userJourneyDiagram",
      "description": "a step in user journey",
      "content": "      Step Title: 5: ActorName",
      "sortingOrder": 1,
      "isPinned": false
    },
    {
      "id": "f48bf6ff-aa0e-42d1-abcd-4394255e856f",
      "categoryId": "ganttChart",
      "description": "simple gantt chart",
      "content": "gantt\n        title A Gantt Diagram\n        dateFormat  YYYY-MM-DD\n        section Section\n        A task           :a1, 2014-01-01, 30d\n        Another task     :after a1  , 20d\n        section Another\n        Task in sec      :2014-01-12  , 12d\n        another task      : 24d",
      "sortingOrder": 0,
      "isPinned": false
    },
    {
      "id": "5962383d-df0a-4083-bb10-66317b57c341",
      "categoryId": "ganttChart",
      "description": "rich gantt chart",
      "content": "gantt\n        dateFormat  YYYY-MM-DD\n        title       Adding GANTT diagram functionality to mermaid\n        excludes    weekends\n    \n        section A section\n        Completed task            :done,    des1, 2014-01-06,2014-01-08\n        Active task               :active,  des2, 2014-01-09, 3d\n        Future task               :         des3, after des2, 5d\n        Future task2              :         des4, after des3, 5d\n    \n        section Critical tasks\n        Completed task in the critical line :crit, done, 2014-01-06,24h\n        Implement parser and jison          :crit, done, after des1, 2d\n        Create tests for parser             :crit, active, 3d\n        Future task in critical line        :crit, 5d\n        Create tests for renderer           :2d\n        Add to mermaid                      :1d\n        Functionality added                 :milestone, 2014-01-25, 0d\n    \n        section Documentation\n        Describe gantt syntax               :active, a1, after des1, 3d\n        Add gantt diagram to demo page      :after a1  , 20h\n        Add another diagram to demo page    :doc1, after a1  , 48h\n    \n        section Last section\n        Describe gantt syntax               :after doc1, 3d\n        Add gantt diagram to demo page      :20h\n        Add another diagram to demo page    :48h",
      "sortingOrder": 1,
      "isPinned": false
    },
    {
      "id": "471223ee-1eec-441d-82d7-083182dbe04e",
      "categoryId": "ganttChart",
      "description": "milestones example",
      "content": "gantt\n        dateFormat HH:mm\n        axisFormat %H:%M\n        Initial milestone : milestone, m1, 17:49,2min\n        taska2 : 10min\n        taska3 : 5min\n        Final milestone : milestone, m2, 18:14, 2min",
      "sortingOrder": 2,
      "isPinned": false
    },
    {
      "id": "eff4b86e-8630-4166-97af-d909e590fca6",
      "categoryId": "pieChart",
      "description": "sample pie chart",
      "content": "pie title /r/obsidianmd posts by type\n        \"Graphs\" : 85\n        \"Dashboards\" : 14\n        \"Tips\" : 1",
      "sortingOrder": 0,
      "isPinned": false
    },
    {
      "id": "0e1e55ca-808b-45f0-b15b-e40edcd49df3",
      "categoryId": "pieChart",
      "description": "sample pie chart with values shown in legend",
      "content": "pie showData title /r/obsidianmd posts by type\n        \"Graphs\" : 85\n        \"Dashboards\" : 14\n        \"Tips\" : 1",
      "sortingOrder": 1,
      "isPinned": false
    },
    {
      "id": "dc24f175-8ca3-48d5-a76a-dda13f07c52c",
      "categoryId": "requirementDiagram",
      "description": "sample requirements diagram",
      "content": "    requirementDiagram\n\n        requirement test_req {\n        id: 1\n        text: the test text.\n        risk: high\n        verifymethod: test\n        }\n    \n        element test_entity {\n        type: simulation\n        }\n    \n        test_entity - satisfies -> test_req",
      "sortingOrder": 0,
      "isPinned": false
    },
    {
      "id": "26e2355d-3181-4cda-931e-5c1af327afee",
      "categoryId": "requirementDiagram",
      "description": "sample requirements diagram",
      "content": "element customElement {\n            type: customType\n            docref: customDocRef\n        }",
      "sortingOrder": 1,
      "isPinned": false
    },
    {
      "id": "ceca2c23-df16-4b63-958d-6dad7d0a2763",
      "categoryId": "requirementDiagram",
      "description": "a requirement with high risk",
      "content": "functionalRequirement myReq {\n            id: reqId\n            text: someText\n            risk: High\n            verifymethod: analysis\n        }",
      "sortingOrder": 2,
      "isPinned": false
    },
    {
      "id": "2b331c7b-74b4-4055-b999-08e290d424f3",
      "categoryId": "requirementDiagram",
      "description": "sample requirements diagram",
      "content": "interfaceRequirement myReq2 {\n            id: reqId\n            text: someText\n            risk: Medium\n            verifymethod: demonstration\n        }",
      "sortingOrder": 3,
      "isPinned": false
    },
    {
      "id": "c73b4816-b77a-4ba1-b1ab-e65697ebf5cb",
      "categoryId": "requirementDiagram",
      "description": "sample requirements diagram",
      "content": "designConstraint myReq3 {\n            id: reqId\n            text: someText\n            risk: Low\n            verifymethod: test\n        }",
      "sortingOrder": 4,
      "isPinned": false
    },
    {
      "id": "5332d823-86d4-4195-9aa1-4ff1e5d4bb37",
      "categoryId": "gitGraph",
      "description": "simple git graph",
      "content": "gitGraph\n        commit\n        commit\n        branch develop\n        checkout develop\n        commit\n        commit\n        checkout main\n        merge develop\n        commit\n        commit",
      "sortingOrder": 0,
      "isPinned": false
    },
    {
      "id": "11d9a4b6-72ea-467c-8acc-5e09408a9762",
      "categoryId": "gitGraph",
      "description": "tagged commit",
      "content": "commit id: \"Normal\" tag: \"v1.0.0\"",
      "sortingOrder": 1,
      "isPinned": false
    },
    {
      "id": "e4c194ce-b8f4-461f-bf9e-e0df1d5c9ec6",
      "categoryId": "gitGraph",
      "description": "reverse commit",
      "content": "commit id: \"Reverse\" type: REVERSE",
      "sortingOrder": 2,
      "isPinned": false
    },
    {
      "id": "0dfa7898-705a-4392-9553-88641f7779cf",
      "categoryId": "gitGraph",
      "description": "highlighted commit",
      "content": "commit id: \"Highlight\" type: HIGHLIGHT",
      "sortingOrder": 3,
      "isPinned": false
    },
    {
      "id": "47e1f8da-6bae-400f-a1e0-eef7e3e6b7da",
      "categoryId": "gitGraph",
      "description": "reverse commit",
      "content": "commit id: \"Reverse\" type: REVERSE",
      "sortingOrder": 4,
      "isPinned": false
    },
    {
      "id": "01e2d8bb-4df4-48d8-8e92-88c125290094",
      "categoryId": "gitGraph",
      "description": "git graph with cherry-pick",
      "content": "gitGraph\n        commit id: \"ZERO\"\n        branch develop\n        commit id:\"A\"\n        checkout main\n        commit id:\"ONE\"\n        checkout develop\n        commit id:\"B\"\n        checkout main\n        commit id:\"TWO\"\n        cherry-pick id:\"A\"\n        commit id:\"THREE\"\n        checkout develop\n        commit id:\"C\"",
      "sortingOrder": 5,
      "isPinned": false
    },
    {
      "id": "12de7949-a255-45e0-bfd9-8a2e5b29b4a2",
      "categoryId": "mindmap",
      "description": "a simple mindmap",
      "content": "mindmap\n        Root\n            A\n              B\n              C",
      "sortingOrder": 1,
      "isPinned": false
    },
    {
      "id": "11de7d7a-bdab-4284-ae39-9e3984800d14",
      "categoryId": "mindmap",
      "description": "square",
      "content": "id[I am a square]",
      "sortingOrder": 2,
      "isPinned": false
    },
    {
      "id": "f0b26c30-1bde-45e4-a0a3-3b29ab9731d5",
      "categoryId": "mindmap",
      "description": "rounded square",
      "content": "id(I am a rounded square)",
      "sortingOrder": 3,
      "isPinned": false
    },
    {
      "id": "9991b3a6-fcf2-44f2-9f4c-d513c7a21fa1",
      "categoryId": "mindmap",
      "description": "circle",
      "content": "id((I am a circle))",
      "sortingOrder": 4,
      "isPinned": false
    },
    {
      "id": "4306fc34-64e7-4b85-aa22-4b1ddc9a7a8d",
      "categoryId": "mindmap",
      "description": "bang",
      "content": "id))I am a bang((",
      "sortingOrder": 5,
      "isPinned": false
    },
    {
      "id": "2e152c5a-bbb6-4316-8d6b-2d572c06ac4b",
      "categoryId": "mindmap",
      "description": "cloud",
      "content": "id)I am a cloud(",
      "sortingOrder": 6,
      "isPinned": false
    },
    {
      "id": "3a358642-c1f0-494e-8744-72022f931d97",
      "categoryId": "mindmap",
      "description": "hexagon",
      "content": "id{{I am a hexagon}}",
      "sortingOrder": 7,
      "isPinned": false
    },
    {
      "id": "8f71381a-4fcd-4c47-8e55-767f56ae0a9a",
      "categoryId": "mindmap",
      "description": "default",
      "content": "I am the default shape",
      "sortingOrder": 8,
      "isPinned": false
    },
    {
      "id": "dec564df-d96b-41e2-918b-f00928c6c499",
      "categoryId": "mindmap",
      "description": "sample mindmap",
      "content": "mindmap\n        root((mindmap))\n          Origins\n            Long history\n            Popularisation\n              British popular psychology author Tony Buzan\n          Research\n            On effectiveness<br/>and features\n            On Automatic creation\n              Uses\n                  Creative techniques\n                  Strategic planning\n                  Argument mapping\n          Tools\n            Pen and paper\n            Mermaid",
      "sortingOrder": 9,
      "isPinned": false
    },
    {
      "id": "27191704-c3e9-403c-874c-8e03550279d0",
      "categoryId": "timeline",
      "description": "sample timeline",
      "content": "timeline\n\t\ttitle History of Social Media Platform\n\t\t2002 : LinkedIn\n\t\t2004 : Facebook\n\t\t\t : Google\n\t\t2005 : Youtube\n\t\t2006 : Twitter",
      "sortingOrder": 1,
      "isPinned": false
    },
    {
      "id": "c41517cf-c7fa-4f5a-ac6c-8bd688b5a8e6",
      "categoryId": "timeline",
      "description": "timeline with grouping",
      "content": "timeline\n\t\ttitle Timeline of Industrial Revolution\n\t\tsection 17th-20th century\n\t\t\tIndustry 1.0 : Machinery, Water power, Steam <br>power\n\t\t\tIndustry 2.0 : Electricity, Internal combustion engine, Mass production\n\t\t\tIndustry 3.0 : Electronics, Computers, Automation\n\t\tsection 21st century\n\t\t\tIndustry 4.0 : Internet, Robotics, Internet of Things\n\t\t\tIndustry 5.0 : Artificial intelligence, Big data,3D printing",
      "sortingOrder": 2,
      "isPinned": false
    },
    {
      "id": "61a0441f-649b-4acf-8420-6ff3338d688a",
      "categoryId": "timeline",
      "description": "timeline with Forest theme. see the docs for additional themes",
      "content": "%%{init: { 'logLevel': 'debug', 'theme': 'forest' } }%%\n\t\ttimeline\n\t\t\ttitle History of Social Media Platform\n\t\t\t  2002 : LinkedIn\n\t\t\t  2004 : Facebook : Google\n\t\t\t  2005 : Youtube\n\t\t\t  2006 : Twitter\n\t\t\t  2007 : Tumblr\n\t\t\t  2008 : Instagram\n\t\t\t  2010 : Pinterest",
      "sortingOrder": 3,
      "isPinned": false
    },
    {
      "id": "0a435a9e-ef37-456e-8f7e-d85589b4add5",
      "categoryId": "quadrantChart",
      "description": "sample quadrant chart",
      "content": "quadrantChart\n\t\ttitle Reach and engagement of campaigns\n\t\tx-axis Low Reach --> High Reach\n\t\ty-axis Low Engagement --> High Engagement\n\t\tquadrant-1 We should expand\n\t\tquadrant-2 Need to promote\n\t\tquadrant-3 Re-evaluate\n\t\tquadrant-4 May be improved\n\t\tCampaign A: [0.3, 0.6]\n\t\tCampaign B: [0.45, 0.23]\n\t\tCampaign C: [0.57, 0.69]\n\t\tCampaign D: [0.78, 0.34]\n\t\tCampaign E: [0.40, 0.34]\n\t\tCampaign F: [0.35, 0.78]",
      "sortingOrder": 1,
      "isPinned": false
    },
    {
      "id": "7821261d-aaab-4489-bc98-ee6995af3a07",
      "categoryId": "quadrantChart",
      "description": "themed quadrant chart",
      "content": "%%{init: {\"quadrantChart\": {\"chartWidth\": 400, \"chartHeight\": 400}, \"themeVariables\": {\"quadrant1TextFill\": \"#ff0000\"} }}%%\n\t\tquadrantChart\n\t\t  x-axis Urgent --> Not Urgent\n\t\t  y-axis Not Important --> \"Important ❤\"\n\t\t  quadrant-1 Plan\n\t\t  quadrant-2 Do\n\t\t  quadrant-3 Delegate\n\t\t  quadrant-4 Delete",
      "sortingOrder": 1,
      "isPinned": false
    },
    {
      "id": "5141f8bc-197d-4607-8bc6-db17dafc966c",
      "categoryId": "c4Diagram",
      "description": "sample C4 diagram (compatible with PlantUML)",
      "content": "C4Context\n\t\ttitle System Context diagram for Internet Banking System\n\t\tEnterprise_Boundary(b0, \"BankBoundary0\") {\n\t\t  Person(customerA, \"Banking Customer A\", \"A customer of the bank, with personal bank accounts.\")\n\t\t  Person(customerB, \"Banking Customer B\")\n\t\t  Person_Ext(customerC, \"Banking Customer C\", \"desc\")\n  \n\t\t  Person(customerD, \"Banking Customer D\", \"A customer of the bank, <br/> with personal bank accounts.\")\n  \n\t\t  System(SystemAA, \"Internet Banking System\", \"Allows customers to view information about their bank accounts, and make payments.\")\n  \n\t\t  Enterprise_Boundary(b1, \"BankBoundary\") {\n  \n\t\t\tSystemDb_Ext(SystemE, \"Mainframe Banking System\", \"Stores all of the core banking information about customers, accounts, transactions, etc.\")\n  \n\t\t\tSystem_Boundary(b2, \"BankBoundary2\") {\n\t\t\t  System(SystemA, \"Banking System A\")\n\t\t\t  System(SystemB, \"Banking System B\", \"A system of the bank, with personal bank accounts. next line.\")\n\t\t\t}\n  \n\t\t\tSystem_Ext(SystemC, \"E-mail system\", \"The internal Microsoft Exchange e-mail system.\")\n\t\t\tSystemDb(SystemD, \"Banking System D Database\", \"A system of the bank, with personal bank accounts.\")\n  \n\t\t\tBoundary(b3, \"BankBoundary3\", \"boundary\") {\n\t\t\t  SystemQueue(SystemF, \"Banking System F Queue\", \"A system of the bank.\")\n\t\t\t  SystemQueue_Ext(SystemG, \"Banking System G Queue\", \"A system of the bank, with personal bank accounts.\")\n\t\t\t}\n\t\t  }\n\t\t}\n  \n\t\tBiRel(customerA, SystemAA, \"Uses\")\n\t\tBiRel(SystemAA, SystemE, \"Uses\")\n\t\tRel(SystemAA, SystemC, \"Sends e-mails\", \"SMTP\")\n\t\tRel(SystemC, customerA, \"Sends e-mails to\")\n  \n\t\tUpdateElementStyle(customerA, $fontColor=\"red\", $bgColor=\"grey\", $borderColor=\"red\")\n\t\tUpdateRelStyle(customerA, SystemAA, $textColor=\"blue\", $lineColor=\"blue\", $offsetX=\"5\")\n\t\tUpdateRelStyle(SystemAA, SystemE, $textColor=\"blue\", $lineColor=\"blue\", $offsetY=\"-10\")\n\t\tUpdateRelStyle(SystemAA, SystemC, $textColor=\"blue\", $lineColor=\"blue\", $offsetY=\"-40\", $offsetX=\"-50\")\n\t\tUpdateRelStyle(SystemC, customerA, $textColor=\"red\", $lineColor=\"red\", $offsetX=\"-50\", $offsetY=\"20\")\n  \n\t\tUpdateLayoutConfig($c4ShapeInRow=\"3\", $c4BoundaryInRow=\"1\")",
      "sortingOrder": 1,
      "isPinned": false
    },
    {
      "id": "63f57f18-61ec-4510-bb7e-5579ee009fdc",
      "categoryId": "sankeyDiagram",
      "description": "",
      "content": "sankey-beta\n        %% source,target,value\n        Electricity grid,Over generation / exports,104.453\n        Electricity grid,Heating and cooling - homes,113.726\n        Electricity grid,H2 conversion,27.14",
      "sortingOrder": 0,
      "isPinned": false
    },
    {
      "id": "e91f41ee-0e12-428e-98ed-d587cba753fe",
      "categoryId": "xyChart",
      "description": "a sample XYChart diagram",
      "content": "xychart-beta\n        title \"Sales Revenue\"\n        x-axis [jan, feb, mar, apr, may, jun, jul, aug, sep, oct, nov, dec]\n        y-axis \"Revenue (in $)\" 4000 --> 11000\n        bar [5000, 6000, 7500, 8200, 9500, 10500, 11000, 10200, 9200, 8500, 7000, 6000]\n        line [5000, 6000, 7500, 8200, 9500, 10500, 11000, 10200, 9200, 8500, 7000, 6000]",
      "sortingOrder": 0,
      "isPinned": false
    },
    {
      "id": "c5657f23-e8e8-4d7f-95b2-8291e0990145",
      "categoryId": "packet",
      "description": "a sample packet diagram",
      "content": "packet-beta\ntitle UDP Packet\n0-15: \"Source Port\"\n16-31: \"Destination Port\"\n32-47: \"Length\"\n48-63: \"Checksum\"\n64-95: \"Data (variable length)\"\n",
      "sortingOrder": 0,
      "isPinned": false
    },
    {
      "id": "eefa2c62-9f32-4935-bdc3-0bf746e34c4d",
      "categoryId": "kanban",
      "description": "a sample kanban diagram",
      "content": "kanban\n  Todo\n    [Create Documentation]\n    docs[Create Blog about the new diagram]\n  [In progress]\n    id6[Create renderer so that it works in all cases. We also add som extra text here for testing purposes. And some more just for the extra flare.]\n  id9[Ready for deploy]\n    id8[Design grammar]@{ assigned: 'knsv' }\n  id10[Ready for test]\n    id4[Create parsing tests]@{ ticket: MC-2038, assigned: 'K.Sveidqvist', priority: 'High' }\n    id66[last item]@{ priority: 'Very Low', assigned: 'knsv' }\n  id11[Done]\n    id5[define getData]\n    id2[Title of diagram is more than 100 chars when user duplicates diagram with 100 char]@{ ticket: MC-2036, priority: 'Very High'}\n    id3[Update DB function]@{ ticket: MC-2037, assigned: knsv, priority: 'High' }\n\n  id12[Can't reproduce]\n    id3[Weird flickering in Firefox]",
      "sortingOrder": 0,
      "isPinned": false
    },
    {
      "id": "6a200848-bbd0-48a4-a5d6-6ddf0b25ca82",
      "categoryId": "block",
      "description": "a sample block diagram",
      "content": "block-beta\ncolumns 1\n  db((\"DB\"))\n  blockArrowId6<[\"&nbsp;&nbsp;&nbsp;\"]>(down)\n  block:ID\n    A\n    B[\"A wide one in the middle\"]\n    C\n  end\n  space\n  D\n  ID --> D\n  C --> D\n  style B fill:#969,stroke:#333,stroke-width:4px\n",
      "sortingOrder": 0,
      "isPinned": false
    },
    {
      "id": "f1579934-6c3d-4407-ade6-6110871463e9",
      "categoryId": "architecture",
      "description": "a sample architecture diagram",
      "content": "architecture-beta\n    group api(cloud)[API]\n\n    service db(database)[Database] in api\n    service disk1(disk)[Storage] in api\n    service disk2(disk)[Storage] in api\n    service server(server)[Server] in api\n\n    db:L -- R:server\n    disk1:T -- B:server\n    disk2:T -- B:db\n",
      "sortingOrder": 0,
      "isPinned": false
    },
    {
      "id": "84a42b36-d274-45ad-9a33-3a8af3192d33",
      "description": "New element",
      "content": "flowchart TD\nStart --> Stop",
      "categoryId": "flowchart",
      "sortingOrder": 0,
      "isPinned": false
    }
  ],
  "customCategories": [],
  "selectedCategoryId": "sequenceDiagram",
  "defaultCategorySortOrders": {},
  "categoryModifications": {}
}